llmflow_ai/__init__.py
llmflow_ai/__main__.py
llmflow_ai/_cli/info.py
llmflow_ai/_cli/list.py
llmflow_ai/_cli/main.py
llmflow_ai/_cli/run.py
llmflow_ai/_util/constants.py
llmflow_ai/configuration/enrichment.py
llmflow_ai-0.0.4.dist-info/LICENSE
llmflow_ai-0.0.4.dist-info/METADATA
llmflow_ai-0.0.4.dist-info/WHEEL
llmflow_ai-0.0.4.dist-info/entry_points.txt
llmflow_ai-0.0.4.dist-info/top_level.txt
llmflow_ai-0.0.4.dist-info/RECORD
